<?xml version="1.0" encoding="UTF-8"?>
<!--
  ============LICENSE_START=======================================================
  ECOMP MSO
  ================================================================================
  Copyright (C) 2017 AT&T Intellectual Property. All rights reserved.
  ================================================================================
  Licensed under the Apache License, Version 2.0 (the "License");
  you may not use this file except in compliance with the License.
  You may obtain a copy of the License at
  
       http://www.apache.org/licenses/LICENSE-2.0
  
  Unless required by applicable law or agreed to in writing, software
  distributed under the License is distributed on an "AS IS" BASIS,
  WITHOUT WARRANTIES OR CONDITIONS OF ANY KIND, either express or implied.
  See the License for the specific language governing permissions and
  limitations under the License.
  ============LICENSE_END=========================================================
  -->

<!DOCTYPE hibernate-configuration PUBLIC
		"-//Hibernate/Hibernate Configuration DTD 3.0//EN"
		"http://www.hibernate.org/dtd/hibernate-configuration-3.0.dtd">
<hibernate-configuration>
    <session-factory>
        <property name="hibernate.dialect">org.hibernate.dialect.MySQL5Dialect</property>
        <property name="hibernate.show_sql">false</property>
        <property name="hibernate.format_sql">true</property>
        <property name="connection.datasource">java:jboss/datasources/mso-requests</property>
		
<!-- 		<property name="hibernate.hbm2ddl.auto">create</property> -->

        <mapping resource="InfraActiveRequests.hbm.xml"></mapping>
        <mapping resource="OperationalEnvServiceModelStatus.hbm.xml"></mapping>
        <mapping resource="OperationalEnvDistributionStatus.hbm.xml"></mapping>
        <mapping resource="OperationStatus.hbm.xml"></mapping>
        <mapping resource="ResourceOperationStatus.hbm.xml"></mapping>
        <mapping resource="SiteStatus.hbm.xml"></mapping>
        <mapping resource="WatchdogDistributionStatus.hbm.xml"></mapping>
        <mapping resource="WatchdogComponentDistributionStatus.hbm.xml"></mapping>
        <mapping resource="WatchdogServiceModVerIdLookup.hbm.xml"></mapping>
    </session-factory>
</hibernate-configuration>
